masspackages/__init__.py
masspackages/mass.py
masspackages/vishwa.py
masspackages/vishwa1.py
masspackages/vishwa2.py
v_data_analyst-1.1.0.dist-info/LICENSE
v_data_analyst-1.1.0.dist-info/METADATA
v_data_analyst-1.1.0.dist-info/WHEEL
v_data_analyst-1.1.0.dist-info/top_level.txt
v_data_analyst-1.1.0.dist-info/RECORD
