Metadata-Version: 2.1
Name: v-data-analyst
Version: 1.1.0
Summary: Basic Understanding of publishing packages to the PYpi
Author: Vishwanath
Author-email: vishwa.automationhub@gmail.com
License: MIT
Classifier: Programming Language :: Python :: 3
Classifier: License :: OSI Approved :: MIT License
Classifier: Operating System :: OS Independent
Requires-Python: >=3.6
License-File: LICENSE
